AUTHORS.rst
CONTRIBUTING.rst
HISTORY.rst
LICENSE
MANIFEST.in
README.rst
setup.cfg
setup.py
negative_inline_editor/__init__.py
negative_inline_editor/filer.py
negative_inline_editor/middleware.py
negative_inline_editor/urls.py
negative_inline_editor/views.py
negative_inline_editor.egg-info/PKG-INFO
negative_inline_editor.egg-info/SOURCES.txt
negative_inline_editor.egg-info/dependency_links.txt
negative_inline_editor.egg-info/not-zip-safe
negative_inline_editor.egg-info/requires.txt
negative_inline_editor.egg-info/top_level.txt
test/test_negative-inline-editor.py