Metadata-Version: 2.1
Name: negative-inline-editor
Version: 0.1.0
Summary: On-site editing for Django
Home-page: https://github.com/negative-space/negative-inline-editor
Author: Alex Rudakov
Author-email: ribozz@gmail.com
License: MIT
Keywords: negative-inline-editor
Platform: UNKNOWN
Classifier: Development Status :: 2 - Pre-Alpha
Classifier: Intended Audience :: Developers
Classifier: License :: OSI Approved :: MIT License
Classifier: Natural Language :: English
Classifier: Programming Language :: Python :: 3
Classifier: Programming Language :: Python :: 3.6
Classifier: Programming Language :: Python :: Implementation :: PyPy
Provides-Extra: filer
